webchanges/__init__.py
webchanges/__main__.py
webchanges/cli.py
webchanges/command.py
webchanges/config.py
webchanges/differs.py
webchanges/filters.py
webchanges/handler.py
webchanges/jobs.py
webchanges/mailer.py
webchanges/main.py
webchanges/py.typed
webchanges/reporters.py
webchanges/storage.py
webchanges/storage_minidb.py
webchanges/util.py
webchanges/worker.py
webchanges/_vendored/__init__.py
webchanges/_vendored/headers.py
webchanges/_vendored/packaging_version.py
webchanges-3.33.0.dist-info/licenses/LICENSE.md
webchanges-3.33.0.dist-info/METADATA
webchanges-3.33.0.dist-info/WHEEL
webchanges-3.33.0.dist-info/entry_points.txt
webchanges-3.33.0.dist-info/top_level.txt
webchanges-3.33.0.dist-info/RECORD
