Metadata-Version: 2.4
Name: webchanges
Version: 3.33.0
Summary: Web Changes Delivered. AI-Summarized. Totally Anonymous.
Author-email: Mike Borsetti <mike+webchanges@borsetti.com>
Maintainer-email: Mike Borsetti <mike+webchanges@borsetti.com>
License: ========
Project-URL: Documentation, https://webchanges.readthedocs.io/
Project-URL: Repository, https://github.com/mborsetti/webchanges/
Project-URL: Changelog, https://webchanges.readthedocs.io/en/stable/changelog.html
Project-URL: Issues, https://github.com/mborsetti/webchanges/issues
Project-URL: CI, https://github.com/mborsetti/webchanges/actions
Keywords: webmonitoring,monitoring
Classifier: Development Status :: 5 - Production/Stable
Classifier: Environment :: Console
Classifier: Intended Audience :: Developers
Classifier: Intended Audience :: End Users/Desktop
Classifier: Intended Audience :: System Administrators
Classifier: License :: OSI Approved :: BSD License
Classifier: License :: OSI Approved :: MIT License
Classifier: Natural Language :: English
Classifier: Operating System :: OS Independent
Classifier: Programming Language :: Python
Classifier: Programming Language :: Python :: 3
Classifier: Programming Language :: Python :: 3 :: Only
Classifier: Programming Language :: Python :: 3.11
Classifier: Programming Language :: Python :: 3.12
Classifier: Programming Language :: Python :: 3.13
Classifier: Programming Language :: Python :: 3.14
Classifier: Programming Language :: Python :: Free Threading
Classifier: Programming Language :: Python :: Free Threading :: 4 - Resilient
Classifier: Programming Language :: Python :: Implementation :: CPython
Classifier: Topic :: Internet
Classifier: Topic :: Internet :: WWW/HTTP
Classifier: Topic :: Internet :: WWW/HTTP :: Indexing/Search
Classifier: Topic :: System :: Monitoring
Classifier: Topic :: Utilities
Classifier: Typing :: Typed
Requires-Python: >=3.11
License-File: LICENSE.md
Requires-Dist: colorama; sys_platform == "win32"
Requires-Dist: cssselect
Requires-Dist: h2
Requires-Dist: html2text
Requires-Dist: httpx
Requires-Dist: lxml
Requires-Dist: markdown2
Requires-Dist: msgpack
Requires-Dist: platformdirs
Requires-Dist: pyyaml
Requires-Dist: tzdata; sys_platform == "win32"
Requires-Dist: zstandard; python_version < "3.14"
Provides-Extra: use-browser
Requires-Dist: playwright; extra == "use-browser"
Requires-Dist: psutil; extra == "use-browser"
Provides-Extra: beautify
Requires-Dist: beautifulsoup4; extra == "beautify"
Requires-Dist: jsbeautifier; extra == "beautify"
Requires-Dist: cssbeautifier; extra == "beautify"
Provides-Extra: bs4
Requires-Dist: beautifulsoup4; extra == "bs4"
Provides-Extra: html5lib
Requires-Dist: html5lib; extra == "html5lib"
Provides-Extra: ical2text
Requires-Dist: vobject; extra == "ical2text"
Provides-Extra: jq
Requires-Dist: jq; os_name != "nt" and extra == "jq"
Provides-Extra: ocr
Requires-Dist: pytesseract; extra == "ocr"
Requires-Dist: Pillow; extra == "ocr"
Provides-Extra: pdf2text
Requires-Dist: pdftotext; extra == "pdf2text"
Provides-Extra: pypdf
Requires-Dist: pypdf; extra == "pypdf"
Provides-Extra: pypdf-crypto
Requires-Dist: pypdf; extra == "pypdf-crypto"
Requires-Dist: cryptography; extra == "pypdf-crypto"
Provides-Extra: deepdiff
Requires-Dist: deepdiff; extra == "deepdiff"
Provides-Extra: deepdiff-xml
Requires-Dist: deepdiff; extra == "deepdiff-xml"
Requires-Dist: xmltodict; extra == "deepdiff-xml"
Provides-Extra: imagediff
Requires-Dist: Pillow; extra == "imagediff"
Provides-Extra: matrix
Requires-Dist: matrix_client; extra == "matrix"
Provides-Extra: pushbullet
Requires-Dist: pushbullet.py; extra == "pushbullet"
Provides-Extra: pushover
Requires-Dist: chump; extra == "pushover"
Provides-Extra: xmpp
Requires-Dist: aioxmpp; extra == "xmpp"
Provides-Extra: redis
Requires-Dist: redis; extra == "redis"
Provides-Extra: requests
Requires-Dist: requests; extra == "requests"
Provides-Extra: safe-password
Requires-Dist: keyring; extra == "safe-password"
Provides-Extra: all
Requires-Dist: webchanges[beautify,bs4,deepdiff_xml,html5lib,ical2text,imagediff,jq,matrix,ocr,pdf2text,pushbullet,pushover,pypdf_crypto,redis,requests,safe_password,use_browser,xmpp]; extra == "all"
Dynamic: license-file
